LICENSE
setup.py
google_sheet_tms/__init__.py
google_sheet_tms/google_sheet_tms.py
google_sheet_tms.egg-info/PKG-INFO
google_sheet_tms.egg-info/SOURCES.txt
google_sheet_tms.egg-info/dependency_links.txt
google_sheet_tms.egg-info/requires.txt
google_sheet_tms.egg-info/top_level.txt