Metadata-Version: 2.4
Name: google_sheet_tms
Version: 0.1.2
Summary: Use Google Sheet as TMS
Author: Walery Wysotsky
Author-email: dev@wysotsky.info
Classifier: Programming Language :: Python :: 3
Classifier: License :: OSI Approved :: MIT License
Classifier: Operating System :: OS Independent
Classifier: Development Status :: 3 - Alpha
Classifier: Intended Audience :: Developers
Classifier: Topic :: Software Development :: Libraries
License-File: LICENSE
Requires-Dist: dotenv
Requires-Dist: gspread
Requires-Dist: oauth2client
Dynamic: author
Dynamic: author-email
Dynamic: classifier
Dynamic: license-file
Dynamic: requires-dist
Dynamic: summary
